aiassistcli/__init__.py
aiassistcli/ai_generate.py
aiassistcli/ai_prompt.py
aiassistcli/check_update.py
aiassistcli/config.py
aiassistcli/history.py
aiassistcli/main.py
aiassistcli/run_prompt.py
aiassistcli/providers/base.py
aiassistcli/providers/gemini_provider.py
aiassistcli/providers/openai_compatible.py
canoaicli-2.0.0.dist-info/METADATA
canoaicli-2.0.0.dist-info/WHEEL
canoaicli-2.0.0.dist-info/entry_points.txt
canoaicli-2.0.0.dist-info/licenses/LICENSE
canoaicli-2.0.0.dist-info/RECORD
