Metadata-Version: 2.4
Name: canoaicli
Version: 2.0.0
Summary: A command-line AI assistant powered by multiple AI providers such as Google Gemini, OpenAI, Anthropic, and DeepSeek
Author-email: carellihoula <carellihoula10@gmail.com>
License-File: LICENSE
Requires-Python: >=3.9
Requires-Dist: google-generativeai
Requires-Dist: openai
Requires-Dist: pyperclip
Requires-Dist: questionary
Requires-Dist: rich
